applipy/__init__.py
applipy/__main__.py
applipy/py.typed
applipy/version.py
applipy/application/__init__.py
applipy/application/apphandle.py
applipy/application/application.py
applipy/application/module.py
applipy/config/__init__.py
applipy/config/config.py
applipy/config/protocol.py
applipy/config/protocols/__init__.py
applipy/config/protocols/docker.py
applipy/config/protocols/environment.py
applipy/logging/__init__.py
applipy/logging/module.py
applipy-2.5.0.dist-info/LICENSE
applipy-2.5.0.dist-info/METADATA
applipy-2.5.0.dist-info/WHEEL
applipy-2.5.0.dist-info/entry_points.txt
applipy-2.5.0.dist-info/top_level.txt
applipy-2.5.0.dist-info/RECORD
